django_simple_bulk_emailer/__init__.py
django_simple_bulk_emailer/admin.py
django_simple_bulk_emailer/apps.py
django_simple_bulk_emailer/forms.py
django_simple_bulk_emailer/models.py
django_simple_bulk_emailer/runtests.py
django_simple_bulk_emailer/urls.py
django_simple_bulk_emailer/views.py
django_simple_bulk_emailer/management/__init__.py
django_simple_bulk_emailer/management/commands/__init__.py
django_simple_bulk_emailer/management/commands/delete_expired_emails.py
django_simple_bulk_emailer/management/commands/delete_expired_stats.py
django_simple_bulk_emailer/management/commands/delete_unsubscribed_users.py
django_simple_bulk_emailer/management/commands/import_sites.py
django_simple_bulk_emailer/management/commands/send_bulk_email.py
django_simple_bulk_emailer/management/commands/sync_mailchimp.py
django_simple_bulk_emailer/management/commands/update_email_stats.py
django_simple_bulk_emailer/migrations/0001_initial.py
django_simple_bulk_emailer/migrations/0002_auto_20210812_1535.py
django_simple_bulk_emailer/migrations/0003_auto_20210824_1148.py
django_simple_bulk_emailer/migrations/0004_bulkemail_update_datetime.py
django_simple_bulk_emailer/migrations/__init__.py
django_simple_bulk_emailer/signals/__init__.py
django_simple_bulk_emailer/signals/handlers.py
django_simple_bulk_emailer/static/.DS_Store
django_simple_bulk_emailer/static/admin/css/django_simple_bulk_emailer.css
django_simple_bulk_emailer/static/django_simple_bulk_emailer/.DS_Store
django_simple_bulk_emailer/static/django_simple_bulk_emailer/css/django_simple_bulk_emailer.css
django_simple_bulk_emailer/static/django_simple_bulk_emailer/css/django_simple_bulk_emailer_preview.css
django_simple_bulk_emailer/static/django_simple_bulk_emailer/images/.DS_Store
django_simple_bulk_emailer/static/django_simple_bulk_emailer/images/file_icon_64x64.png
django_simple_bulk_emailer/static/django_simple_bulk_emailer/js/.DS_Store
django_simple_bulk_emailer-0.2.7.dist-info/LICENSE
django_simple_bulk_emailer-0.2.7.dist-info/METADATA
django_simple_bulk_emailer-0.2.7.dist-info/WHEEL
django_simple_bulk_emailer-0.2.7.dist-info/top_level.txt
django_simple_bulk_emailer-0.2.7.dist-info/zip-safe
django_simple_bulk_emailer-0.2.7.dist-info/RECORD
