Metadata-Version: 2.1
Name: django_simple_bulk_emailer
Version: 0.2.7
Summary: A Django app for sending bulk email
Home-page: https://github.com/jonathanrickard/django-simple-bulk-emailer
Author: Jonathan Rickard
Author-email: jonathan@jonathanrickard.com
License: MIT License
Keywords: django,email
Classifier: Environment :: Web Environment
Classifier: Framework :: Django
Classifier: Framework :: Django :: 4.2
Classifier: Framework :: Django :: 5.0
Classifier: Operating System :: OS Independent
Classifier: Programming Language :: Python
Classifier: Programming Language :: Python :: 3
Classifier: Programming Language :: Python :: 3.9
Classifier: Programming Language :: Python :: 3.10
Classifier: Programming Language :: Python :: 3.11
Classifier: Programming Language :: Python :: 3.12
Classifier: Intended Audience :: Developers
Classifier: Topic :: Internet :: WWW/HTTP
Classifier: License :: OSI Approved :: MIT License
License-File: LICENSE
Requires-Dist: Django <5.1,>=4.2
Requires-Dist: django-admin-sortable2 >=2.1.8
Requires-Dist: django-ckeditor >=6.2
Requires-Dist: django-simple-file-handler >=0.3.5
Requires-Dist: mailchimp3 >=3.0
Requires-Dist: Pillow >=9.0
Requires-Dist: requests >=2.27
